{
    "results": [
        {
            "elevation": 7.997093677520752,
            "location": {
                "lat": 53.34384019999999,
                "lng": -6.264253699999999
            },
            "resolution": 4.771975994110107
        },
        {
            "elevation": 5.225362777709961,
            "location": {
                "lat": 53.34448420319321,
                "lng": -6.265809745303077
            },
            "resolution": 4.771975994110107
        },
        {
            "elevation": 5.434278964996338,
            "location": {
                "lat": 53.34512818614621,
                "lng": -6.267365837611277
            },
            "resolution": 4.771975994110107
        },
        {
            "elevation": 0.09548846632242203,
            "location": {
                "lat": 53.34577214885791,
                "lng": -6.268921976925648
            },
            "resolution": 4.771975994110107
        },
        {
            "elevation": 3.778403520584106,
            "location": {
                "lat": 53.34641609132723,
                "lng": -6.270478163247236
            },
            "resolution": 4.771975994110107
        },
        {
            "elevation": 4.272248268127441,
            "location": {
                "lat": 53.34706001355308,
                "lng": -6.272034396577086
            },
            "resolution": 4.771975994110107
        },
        {
            "elevation": 6.206181526184082,
            "location": {
                "lat": 53.34770391553437,
                "lng": -6.273590676916242
            },
            "resolution": 4.771975994110107
        },
        {
            "elevation": 7.037405490875244,
            "location": {
                "lat": 53.34834779727,
                "lng": -6.275147004265748
            },
            "resolution": 4.771975994110107
        },
        {
            "elevation": 6.753762722015381,
            "location": {
                "lat": 53.34899165875891,
                "lng": -6.276703378626652
            },
            "resolution": 4.771975994110107
        },
        {
            "elevation": 8.080404281616211,
            "location": {
                "lat": 53.3496355,
                "lng": -6.278259799999999
            },
            "resolution": 4.771975994110107
        }
    ],
    "status": "OK"
}