{
    "results": [
        {
            "elevation": 15.30106353759766,
            "location": {
                "lat": 53.33598929999999,
                "lng": -6.269129699999999
            },
            "resolution": 4.771975994110107
        },
        {
            "elevation": 13.32281398773193,
            "location": {
                "lat": 53.33686163203615,
                "lng": -6.268588010873622
            },
            "resolution": 4.771975994110107
        },
        {
            "elevation": 12.32097721099854,
            "location": {
                "lat": 53.33773396161926,
                "lng": -6.268046299588011
            },
            "resolution": 4.771975994110107
        },
        {
            "elevation": 11.17694664001465,
            "location": {
                "lat": 53.33860628874911,
                "lng": -6.267504566141613
            },
            "resolution": 4.771975994110107
        },
        {
            "elevation": 13.66740989685059,
            "location": {
                "lat": 53.33947861342553,
                "lng": -6.266962810532883
            },
            "resolution": 4.771975994110107
        },
        {
            "elevation": 13.08443737030029,
            "location": {
                "lat": 53.34035093564836,
                "lng": -6.26642103276027
            },
            "resolution": 4.771975994110107
        },
        {
            "elevation": 12.10991191864014,
            "location": {
                "lat": 53.34122325541738,
                "lng": -6.26587923282222
            },
            "resolution": 4.771975994110107
        },
        {
            "elevation": 8.986064910888672,
            "location": {
                "lat": 53.34209557273246,
                "lng": -6.265337410717194
            },
            "resolution": 4.771975994110107
        },
        {
            "elevation": 10.15316104888916,
            "location": {
                "lat": 53.34296788759339,
                "lng": -6.264795566443636
            },
            "resolution": 4.771975994110107
        },
        {
            "elevation": 7.997093677520752,
            "location": {
                "lat": 53.34384019999999,
                "lng": -6.264253699999999
            },
            "resolution": 4.771975994110107
        }
    ],
    "status": "OK"
}