{
    "results": [
        {
            "elevation": 18.98980522155762,
            "location": {
                "lat": 53.3579182,
                "lng": -6.264458899999999
            },
            "resolution": 4.771975994110107
        },
        {
            "elevation": 18.22964096069336,
            "location": {
                "lat": 53.3573205558308,
                "lng": -6.26436815648778
            },
            "resolution": 4.771975994110107
        },
        {
            "elevation": 18.2481632232666,
            "location": {
                "lat": 53.3567229115928,
                "lng": -6.26427741552058
            },
            "resolution": 4.771975994110107
        },
        {
            "elevation": 17.28204917907715,
            "location": {
                "lat": 53.35612526728596,
                "lng": -6.264186677098268
            },
            "resolution": 4.771975994110107
        },
        {
            "elevation": 16.14369583129883,
            "location": {
                "lat": 53.35552762291032,
                "lng": -6.26409594122072
            },
            "resolution": 4.771975994110107
        },
        {
            "elevation": 15.0163745880127,
            "location": {
                "lat": 53.35492997846587,
                "lng": -6.264005207887808
            },
            "resolution": 4.771975994110107
        },
        {
            "elevation": 13.46245574951172,
            "location": {
                "lat": 53.35433233395259,
                "lng": -6.263914477099406
            },
            "resolution": 4.771975994110107
        },
        {
            "elevation": 12.43639183044434,
            "location": {
                "lat": 53.35373468937053,
                "lng": -6.26382374885539
            },
            "resolution": 4.771975994110107
        },
        {
            "elevation": 4.37383508682251,
            "location": {
                "lat": 53.35313704471967,
                "lng": -6.263733023155631
            },
            "resolution": 4.771975994110107
        },
        {
            "elevation": 6.331956386566162,
            "location": {
                "lat": 53.3525394,
                "lng": -6.263642300000001
            },
            "resolution": 4.771975994110107
        }
    ],
    "status": "OK"
}