{
    "results": [
        {
            "elevation": 15.22939968109131,
            "location": {
                "lat": 53.356787,
                "lng": -6.2620292
            },
            "resolution": 4.771975994110107
        },
        {
            "elevation": 9.44704818725586,
            "location": {
                "lat": 53.35409061305933,
                "lng": -6.261404006001327
            },
            "resolution": 4.771975994110107
        },
        {
            "elevation": 5.142482280731201,
            "location": {
                "lat": 53.3513942228521,
                "lng": -6.260778891099119
            },
            "resolution": 4.771975994110107
        },
        {
            "elevation": 4.350785732269287,
            "location": {
                "lat": 53.34869782937908,
                "lng": -6.260153855275692
            },
            "resolution": 4.771975994110107
        },
        {
            "elevation": 4.795668601989746,
            "location": {
                "lat": 53.34600143264097,
                "lng": -6.259528898513369
            },
            "resolution": 4.771975994110107
        },
        {
            "elevation": 5.808966159820557,
            "location": {
                "lat": 53.34330503263853,
                "lng": -6.25890402079448
            },
            "resolution": 4.771975994110107
        },
        {
            "elevation": 10.04653549194336,
            "location": {
                "lat": 53.34060862937249,
                "lng": -6.258279222101359
            },
            "resolution": 4.771975994110107
        },
        {
            "elevation": 11.89638900756836,
            "location": {
                "lat": 53.33791222284356,
                "lng": -6.257654502416343
            },
            "resolution": 4.771975994110107
        },
        {
            "elevation": 14.42030811309814,
            "location": {
                "lat": 53.33521581305249,
                "lng": -6.257029861721772
            },
            "resolution": 4.771975994110107
        },
        {
            "elevation": 13.90142250061035,
            "location": {
                "lat": 53.3325194,
                "lng": -6.2564053
            },
            "resolution": 4.771975994110107
        }
    ],
    "status": "OK"
}