{
    "results": [
        {
            "elevation": 43.45537567138672,
            "location": {
                "lat": 53.32650889999999,
                "lng": -6.317537299999998
            },
            "resolution": 19.08790397644043
        },
        {
            "elevation": 36.44991683959961,
            "location": {
                "lat": 53.32888544073483,
                "lng": -6.312111185354784
            },
            "resolution": 19.08790397644043
        },
        {
            "elevation": 30.76694679260254,
            "location": {
                "lat": 53.33126173528861,
                "lng": -6.306684466170612
            },
            "resolution": 19.08790397644043
        },
        {
            "elevation": 22.23169708251953,
            "location": {
                "lat": 53.33363778361259,
                "lng": -6.301257142390424
            },
            "resolution": 19.08790397644043
        },
        {
            "elevation": 20.27373123168945,
            "location": {
                "lat": 53.33601358565802,
                "lng": -6.295829213957175
            },
            "resolution": 19.08790397644043
        },
        {
            "elevation": 22.21443176269531,
            "location": {
                "lat": 53.33838914137614,
                "lng": -6.290400680813852
            },
            "resolution": 4.771975994110107
        },
        {
            "elevation": 18.93660926818848,
            "location": {
                "lat": 53.34076445071817,
                "lng": -6.284971542903444
            },
            "resolution": 4.771975994110107
        },
        {
            "elevation": 16.44048690795898,
            "location": {
                "lat": 53.34313951363536,
                "lng": -6.279541800168974
            },
            "resolution": 4.771975994110107
        },
        {
            "elevation": 0.0839693546295166,
            "location": {
                "lat": 53.34551433007889,
                "lng": -6.274111452553473
            },
            "resolution": 4.771975994110107
        },
        {
            "elevation": 3.946223735809326,
            "location": {
                "lat": 53.34788890000001,
                "lng": -6.268680499999999
            },
            "resolution": 4.771975994110107
        }
    ],
    "status": "OK"
}